cloakbits/__init__.py
cloakbits/exceptions.py
cloakbits/utils.py
cloakbits/api/__init__.py
cloakbits/api/client.py
cloakbits/api/test_client.py
cloakbits/manager/__init__.py
cloakbits/manager/_base.py
cloakbits/manager/manager.py
cloakbits/manager/session.py
cloakbits/manager/test_manager.py
cloakbits/manager/test_session.py
cloakbits-0.0.3.dist-info/LICENSE
cloakbits-0.0.3.dist-info/METADATA
cloakbits-0.0.3.dist-info/WHEEL
cloakbits-0.0.3.dist-info/top_level.txt
cloakbits-0.0.3.dist-info/RECORD
