Metadata-Version: 2.1
Name: cloakbits
Version: 0.0.3
Summary: A utility for managing Cloakbits stealth sessions.
Home-page: https://github.com/cloakbits/cloakbits-python
Author: Cloakbits
Author-email: dev@cloakbits.co
License: UNKNOWN
Platform: UNKNOWN
Classifier: Programming Language :: Python :: 3
Classifier: License :: OSI Approved :: MIT License
Classifier: Operating System :: OS Independent
Requires-Python: >=3.8
Requires-Dist: aiohttp (==3.7.3)
Requires-Dist: dacite
Requires-Dist: pydantic
Provides-Extra: test
Requires-Dist: pytest ; extra == 'test'
Requires-Dist: pytest-watch ; extra == 'test'
Requires-Dist: tox ; extra == 'test'
